novelSpider/__init__.py
novelSpider/task.py
novelSpider/app/__init__.py
novelSpider/app/novelDownloader.py
novelSpider/app/novelTools/__init__.py
novelSpider/app/novelTools/novelLoger.py
novelSpider/app/novelTools/novelORM.py
novelSpider/app/novelTools/novelParser.py
novelSpider/app/novelTools/novelSpider.py
novelSpider-0.0.13.dist-info/DESCRIPTION.rst
novelSpider-0.0.13.dist-info/METADATA
novelSpider-0.0.13.dist-info/RECORD
novelSpider-0.0.13.dist-info/WHEEL
novelSpider-0.0.13.dist-info/metadata.json
novelSpider-0.0.13.dist-info/top_level.txt
