Metadata-Version: 2.0
Name: novelSpider
Version: 0.0.13
Summary: 采集中文小说网站的爬虫
Home-page: https://github.com/gugutianle/novelSpider
Author: gugutianle
Author-email: gugutianle@ggo.la
License: MIT License
Platform: any
Classifier: Programming Language :: Python
Classifier: Development Status :: 3 - Alpha
Classifier: Intended Audience :: Developers
Classifier: License :: OSI Approved :: MIT License
Classifier: Programming Language :: Python :: 2.7
Requires-Dist: Cython (>=0.29.7)
Requires-Dist: SQLAlchemy (==1.3.1)
Requires-Dist: beautifulsoup4 (==4.6.3)
Requires-Dist: lxml (==4.3.0)
Requires-Dist: mysqlclient (==1.3.7)
Requires-Dist: requests (==2.20.1)
